nodesty_api_client-1.1.2.dist-info/licenses/LICENSE
src/nodesty_api_client/__init__.py
src/nodesty_api_client/client.py
src/nodesty_api_client/models/__init__.py
src/nodesty_api_client/models/dedicated.py
src/nodesty_api_client/models/firewall.py
src/nodesty_api_client/models/shared.py
src/nodesty_api_client/models/user.py
src/nodesty_api_client/models/vps.py
src/nodesty_api_client/services/__init__.py
src/nodesty_api_client/services/base_service.py
src/nodesty_api_client/services/dedicated.py
src/nodesty_api_client/services/firewall.py
src/nodesty_api_client/services/user.py
src/nodesty_api_client/services/vps.py
nodesty_api_client-1.1.2.dist-info/METADATA
nodesty_api_client-1.1.2.dist-info/WHEEL
nodesty_api_client-1.1.2.dist-info/top_level.txt
nodesty_api_client-1.1.2.dist-info/RECORD
