Metadata-Version: 2.4
Name: nodesty-api-client
Version: 1.1.2
Summary: nodesty.com için Python API istemci kütüphanesi
Author-email: Staticius <astaticdev@gmail.com>
License-Expression: MIT
Project-URL: Homepage, https://github.com/nodestycom/python-api-client
Project-URL: Bug Tracker, https://github.com/nodestycom/python-api-client/issues
Classifier: Programming Language :: Python :: 3
Classifier: Operating System :: OS Independent
Classifier: Development Status :: 3 - Alpha
Classifier: Intended Audience :: Developers
Classifier: Topic :: Software Development :: Libraries :: Python Modules
Requires-Python: >=3.9
License-File: LICENSE
Requires-Dist: httpx
Requires-Dist: pydantic>=2.0
Dynamic: license-file
